{
  "AWSTemplateFormatVersion": "2010-09-09",
  "Description": "The AWS CloudFormation template for this Serverless application's resources outside of Lambdas and Api Gateway",
  "Parameters": {
    "ProjectName": {
      "Type": "String",
      "AllowedValues": []
    },
    "ProjectDomain": {
      "Type": "String",
      "Default": "myapp.com"
    },
    "Stage": {
      "Type": "String",
      "AllowedValues": [
      ]
    },
    "DataModelStage": {
      "Type": "String",
      "AllowedValues": [
      ]
    },
    "NotificationEmail": {
      "Type": "String",
      "Default": "you@you.com"
    },
    "DynamoRWThroughput": {
      "Type": "String",
      "Default": "1"
    }
  },
  "Metadata": {
      "AWS::CloudFormation::Interface": {
          "ParameterGroups": [
              {
              "Label": {"default": "Project Settings"},
              "Parameters": ["ProjectName", "ProjectDomain", "Stage", "DataModelStage"]
              },
              {
              "Label": {"default": "Monitoring"},
              "Parameters": ["NotificationEmail"]
              },
              {
              "Label": {"default": "Database Settings (DynamoDB)"},
              "Parameters": ["DynamoRWThroughput"]
              }
          ]
      }
  },
  "Resources": {
    "IamRoleLambda": {
      "Type": "AWS::IAM::Role",
      "Properties": {
        "AssumeRolePolicyDocument": {
          "Version": "2012-10-17",
          "Statement": [
            {
              "Effect": "Allow",
              "Principal": {
                "Service": [
                  "lambda.amazonaws.com"
                ]
              },
              "Action": [
                "sts:AssumeRole"
              ]
            }
          ]
        },
        "Path": "/"
      }
    },
    "IamPolicyLambda": {
      "Type": "AWS::IAM::Policy",
      "Properties": {
        "PolicyName": {
          "Fn::Join": [
            "_-_",
            [
              {
                "Ref": "Stage"
              },
              {
                "Ref": "ProjectName"
              },
              "lambda"
            ]
          ]
        },
        "PolicyDocument": {
          "Version": "2012-10-17",
          "Statement": [
            {
              "Effect": "Allow",
              "Action": [
                "logs:CreateLogGroup",
                "logs:CreateLogStream",
                "logs:PutLogEvents"
              ],
              "Resource": {
                "Fn::Join": [
                  ":",
                  [
                    "arn:aws:logs",
                    {
                      "Ref": "AWS::Region"
                    },
                    "*:*"
                  ]
                ]
              }
            }
          ]
        },
        "Roles": [
          {
            "Ref": "IamRoleLambda"
          }
        ],
        "Groups": [
          {
            "Ref": "IamGroupLambda"
          }
        ]
      }
    }
  },
  "Outputs": {
    "IamRoleArnLambda": {
      "Description": "ARN of the lambda IAM role",
      "Value": {
        "Fn::GetAtt": [
          "IamRoleLambda",
          "Arn"
        ]
      }
    }
  }
}